mp3metadata.py
mp3metadata-1.0.1.dist-info/LICENSE
mp3metadata-1.0.1.dist-info/METADATA
mp3metadata-1.0.1.dist-info/WHEEL
mp3metadata-1.0.1.dist-info/top_level.txt
mp3metadata-1.0.1.dist-info/RECORD
