Metadata-Version: 2.1
Name: mp3metadata
Version: 1.0.1
Summary: Tool for the manipulation and creation of metadata in MP3 files.
Author: Finn Roy
License: GNU GENERAL PUBLIC LICENSE
Keywords: metadata,mp3,mutagen
Classifier: License :: OSI Approved :: GNU General Public License v3 (GPLv3)
Classifier: Programming Language :: Python
Classifier: Programming Language :: Python :: 3
Requires-Python: >=3.7
License-File: LICENSE
Requires-Dist: mutagen
